[{"name":"page_dialog","qualifiedName":"page_dialog","href":"page_dialog/page_dialog-library.html","type":"library","overriddenDepth":0,"packageName":"page_dialog"},{"name":"PageDialogWeb","qualifiedName":"page_dialog.PageDialogWeb","href":"page_dialog/PageDialogWeb-class.html","type":"class","overriddenDepth":0,"packageName":"page_dialog","enclosedBy":{"name":"page_dialog","type":"library"}},{"name":"PageDialogWeb","qualifiedName":"page_dialog.PageDialogWeb.PageDialogWeb","href":"page_dialog/PageDialogWeb/PageDialogWeb.html","type":"constructor","overriddenDepth":0,"packageName":"page_dialog","enclosedBy":{"name":"PageDialogWeb","type":"class"}},{"name":"handleMethodCall","qualifiedName":"page_dialog.PageDialogWeb.handleMethodCall","href":"page_dialog/PageDialogWeb/handleMethodCall.html","type":"method","overriddenDepth":0,"packageName":"page_dialog","enclosedBy":{"name":"PageDialogWeb","type":"class"}},{"name":"registerWith","qualifiedName":"page_dialog.PageDialogWeb.registerWith","href":"page_dialog/PageDialogWeb/registerWith.html","type":"method","overriddenDepth":0,"packageName":"page_dialog","enclosedBy":{"name":"PageDialogWeb","type":"class"}},{"name":"showPageDialog","qualifiedName":"page_dialog.showPageDialog","href":"page_dialog/showPageDialog.html","type":"function","overriddenDepth":0,"packageName":"page_dialog","enclosedBy":{"name":"page_dialog","type":"library"}}]
